libra/__init__.py
libra/datasets.py
libra/queries.py
libra/dashboard/LibEDA.py
libra/dashboard/__init__.py
libra/dashboard/auto_eda.py
libra/data_generation/__init__.py
libra/data_generation/dataGen.py
libra/data_generation/dataset_labelmatcher.py
libra/data_generation/grammartree.py
libra/dev_pipeliner/__init__.py
libra/dev_pipeliner/pipeline_sample.py
libra/dev_pipeliner/regression_split_functions.py
libra/modeling/__init__.py
libra/modeling/prediction_model_creation.py
libra/modeling/tuner.py
libra/plotting/__init__.py
libra/plotting/generate_plots.py
libra/plotting/nonkeras_generate_plots.py
libra/preprocessing/NLP_preprocessing.py
libra/preprocessing/__init__.py
libra/preprocessing/data_preprocessor.py
libra/preprocessing/data_reader.py
libra/preprocessing/image_caption_helpers.py
libra/preprocessing/image_preprocessor.py
libra/query/__init__.py
libra/query/classification_models.py
libra/query/dimensionality_red_queries.py
libra/query/feedforward_nn.py
libra/query/generative_models.py
libra/query/nlp_queries.py
libra/query/recommender_systems.py
libra/query/supplementaries.py
libra/query/unused_functions.py
libra-1.2.5.dist-info/LICENSE.txt
libra-1.2.5.dist-info/METADATA
libra-1.2.5.dist-info/WHEEL
libra-1.2.5.dist-info/top_level.txt
libra-1.2.5.dist-info/RECORD
