Metadata-Version: 2.1
Name: libra
Version: 1.2.5
Summary: Ergonomic machine learning
Home-page: https://github.com/Palashio/libra
Author: Palash Shah
Author-email: ps9cmk@virginia.edu
License: UNKNOWN
Platform: UNKNOWN
Classifier: Programming Language :: Python :: 3
Classifier: License :: OSI Approved :: MIT License
Classifier: Operating System :: OS Independent
Requires-Python: >=3.6
Requires-Dist: colorama
Requires-Dist: transformers (==3.0.2)
Requires-Dist: tensorflowjs
Requires-Dist: keras (==2.4.3)
Requires-Dist: numpy
Requires-Dist: pandas
Requires-Dist: sklearn
Requires-Dist: matplotlib
Requires-Dist: tabulate
Requires-Dist: textblob
Requires-Dist: seaborn
Requires-Dist: keras-tuner
Requires-Dist: jellyfish
Requires-Dist: spacy
Requires-Dist: autocorrect
Requires-Dist: pillow
Requires-Dist: prince
Requires-Dist: opencv-python
Requires-Dist: nltk
Requires-Dist: download
Requires-Dist: altair (==4.1.0)
Requires-Dist: streamlit (==0.64.0)
Requires-Dist: xgboost
Requires-Dist: tensorflow-gpu (==2.3.1)
